kbs/cli.py
kbs/secret.py
kbs-0.1.2.dist-info/entry_points.txt
kbs-0.1.2.dist-info/WHEEL
kbs-0.1.2.dist-info/METADATA
kbs-0.1.2.dist-info/RECORD
