Metadata-Version: 2.1
Name: kbs
Version: 0.1.2
Summary: kbs is a command line tool to work with kubernetes secrets
Author: Steinn Eldjárn Sigurðarson
Author-email: steinnes@gmail.com
Requires-Python: >=3.9,<4.0
Classifier: Programming Language :: Python :: 3
Classifier: Programming Language :: Python :: 3.10
Classifier: Programming Language :: Python :: 3.9
Requires-Dist: click (>=8.0.4,<9.0.0)
Requires-Dist: pykube-ng (>=22.7.0,<23.0.0)
